Metadata-Version: 1.0
Name: sa-up-test
Version: 1.0.1
Summary: Tools used by hy~
Home-page: https://pypi.org/project/sa-up_test/
Author: UNKNOWN
Author-email: UNKNOWN
License: UNKNOWN
Platform: any
